<?xml version="1.0" encoding="UTF-8" standalone="yes"?>
<portal overlay="true">
    <name>3dxToolsAdminQueueObjectsPowerView</name>
    <symbolicName>portal_3dxToolsAdminQueueObjectsPowerView</symbolicName>
    <dataObjectType>portal</dataObjectType>
    <description>3dxtool Admin Queue Objects PowerView</description>
    <label></label>
    <hidden>false</hidden>
    <href></href>
    <alt></alt>
    <userAccess/>
    <items>
        <item>3dxToolsAdminQueueObjectsChannel</item>
    </items>
    <settings>
        <setting>
            <settingName>Registered Suite</settingName>
            <settingValue>drV6Tools</settingValue>
        </setting>
    </settings>
    <properties/>
</portal>
