<?xml version="1.0" encoding="UTF-8" standalone="yes"?>
<portal overlay="true">
    <name>FTRProductContextViewGBOMPartTablePortal</name>
    <symbolicName>portal_FTRProductContextViewGBOMPartTablePortal</symbolicName>
    <dataObjectType>portal</dataObjectType>
    <description></description>
    <label></label>
    <hidden>false</hidden>
    <href></href>
    <alt></alt>
    <userAccess/>
    <items>
        <item>FTRProductContextViewGBOMPartTableChannel</item>
    </items>
    <settings>
        <setting>
            <settingName>Registered Suite</settingName>
            <settingValue>Configuration</settingValue>
        </setting>
    </settings>
    <properties/>
</portal>
