<?xml version="1.0" encoding="UTF-8" standalone="yes"?>
<relationship overlay="true">
    <name>RDFPredicate</name>
    <symbolicName>relationship_RDFPredicate</symbolicName>
    <dataObjectType>relationship</dataObjectType>
    <description>This reltype connects the RDFResource (subject) to an RDFResource/RDFLiteral (object) to form a Tag</description>
    <parentName></parentName>
    <hidden>false</hidden>
    <abstract>false</abstract>
    <preventDuplicates>false</preventDuplicates>
    <attributes>
        <attribute>RDFUri</attribute>
        <attribute>RDFAltName</attribute>
    </attributes>
    <fromConnection>
        <meaning>The subject of the predicate</meaning>
        <cardinality>N</cardinality>
        <revision>none</revision>
        <clone>none</clone>
        <propagateModify>false</propagateModify>
        <propagateConnectDisconnect>true</propagateConnectDisconnect>
        <types>
            <type>RDFResource</type>
        </types>
        <relationships/>
    </fromConnection>
    <toConnection>
        <meaning>The object of the predicate</meaning>
        <cardinality>N</cardinality>
        <revision>none</revision>
        <clone>none</clone>
        <propagateModify>false</propagateModify>
        <propagateConnectDisconnect>true</propagateConnectDisconnect>
        <types>
            <type>RDFLiteral</type>
            <type>RDFResource</type>
        </types>
        <relationships/>
    </toConnection>
    <triggers/>
    <properties/>
</relationship>
