<?xml version="1.0" encoding="UTF-8" standalone="yes"?>
<relationship overlay="true">
    <name>Workflow Task</name>
    <symbolicName>relationship_WorkflowTask</symbolicName>
    <dataObjectType>relationship</dataObjectType>
    <description>This is the relationship connects Workflow object and Workflow Task.</description>
    <parentName></parentName>
    <hidden>false</hidden>
    <abstract>false</abstract>
    <preventDuplicates>false</preventDuplicates>
    <attributes/>
    <fromConnection>
        <meaning></meaning>
        <cardinality>One</cardinality>
        <revision>none</revision>
        <clone>none</clone>
        <propagateModify>false</propagateModify>
        <propagateConnectDisconnect>true</propagateConnectDisconnect>
        <types>
            <type>Workflow</type>
        </types>
        <relationships/>
    </fromConnection>
    <toConnection>
        <meaning></meaning>
        <cardinality>N</cardinality>
        <revision>none</revision>
        <clone>none</clone>
        <propagateModify>false</propagateModify>
        <propagateConnectDisconnect>true</propagateConnectDisconnect>
        <types>
            <type>Workflow Task</type>
        </types>
        <relationships/>
    </toConnection>
    <triggers/>
    <properties/>
</relationship>
