<?xml version="1.0" encoding="UTF-8" standalone="yes"?>
<command overlay="true">
    <name>AEFLifecycleMassPromote</name>
    <symbolicName>command_AEFLifecycleMassPromote</symbolicName>
    <dataObjectType>command</dataObjectType>
    <description>Command to do Mass Promote</description>
    <label>emxFramework.Common.MassPromote</label>
    <hidden>false</hidden>
    <href>${COMMON_DIR}/emxMassPromoteDemote.jsp?cmd=Promote</href>
    <alt></alt>
    <code></code>
    <settings>
        <setting>
            <settingName>Image</settingName>
            <settingValue>${COMMON_DIR}/images/iconActionPromote.png</settingValue>
        </setting>
        <setting>
            <settingName>Registered Suite</settingName>
            <settingValue>Framework</settingValue>
        </setting>
        <setting>
            <settingName>Row Select</settingName>
            <settingValue>multi</settingValue>
        </setting>
        <setting>
            <settingName>Submit</settingName>
            <settingValue>true</settingValue>
        </setting>
        <setting>
            <settingName>Target Location</settingName>
            <settingValue>listHidden</settingValue>
        </setting>
    </settings>
    <userAccess/>
    <properties/>
</command>
