<?xml version="1.0" encoding="UTF-8" standalone="yes"?>
<command overlay="true">
    <name>APP3DShapePromoteEvent</name>
    <symbolicName>command_APP3DShapePromoteEvent</symbolicName>
    <dataObjectType>command</dataObjectType>
    <description>When 3DShape is promoted</description>
    <label>emxComponents.Notification.Event.Promoted</label>
    <hidden>false</hidden>
    <href></href>
    <alt></alt>
    <code></code>
    <settings>
        <setting>
            <settingName>Event Type</settingName>
            <settingValue>Promoted</settingValue>
        </setting>
        <setting>
            <settingName>Registered Suite</settingName>
            <settingValue>Components</settingValue>
        </setting>
    </settings>
    <userAccess/>
    <properties/>
</command>
