<?xml version="1.0" encoding="UTF-8" standalone="yes"?>
<command overlay="true">
    <name>BOMRollupView</name>
    <symbolicName>command_BOMRollupView</symbolicName>
    <dataObjectType>command</dataObjectType>
    <description></description>
    <label>emxEngineeringCentral.command.Rollup</label>
    <hidden>false</hidden>
    <href>${SUITE_DIR}/emxEngrBOMIntermediateProcess.jsp?BOMViewMode=Rollup</href>
    <alt>emxEngineeringCentral.command.Rollup</alt>
    <code></code>
    <settings>
        <setting>
            <settingName>Access Function</settingName>
            <settingValue>displayForInstanceView</settingValue>
        </setting>
        <setting>
            <settingName>Access Program</settingName>
            <settingValue>enoUnifiedBOM</settingValue>
        </setting>
        <setting>
            <settingName>Image</settingName>
            <settingValue>${COMMON_DIR}/images/iconActionQuantityRollup.png</settingValue>
        </setting>
        <setting>
            <settingName>Licensed Product</settingName>
            <settingValue>ENO_ENG_TP,ENO_TBE_TP,ENO_MCC_TP,ENO_XCE_TP</settingValue>
        </setting>
        <setting>
            <settingName>Mode</settingName>
            <settingValue>view</settingValue>
        </setting>
        <setting>
            <settingName>Registered Suite</settingName>
            <settingValue>EngineeringCentral</settingValue>
        </setting>
        <setting>
            <settingName>Submit</settingName>
            <settingValue>true</settingValue>
        </setting>
        <setting>
            <settingName>Target Location</settingName>
            <settingValue>listHidden</settingValue>
        </setting>
    </settings>
    <userAccess/>
    <properties/>
</command>
