<?xml version="1.0" encoding="UTF-8" standalone="yes"?>
<command overlay="true">
    <name>IssueAssigneeTreeCategory</name>
    <symbolicName>command_IssueAssigneeTreeCategory</symbolicName>
    <dataObjectType>command</dataObjectType>
    <description>Issue AssigneeCommand Object</description>
    <label>emxComponents.Command.AssigneeList</label>
    <hidden>false</hidden>
    <href>${COMMON_DIR}/emxIndentedTable.jsp?table=IssueAssigneeList&amp;toolbar=IssueAssigneeListToolBar&amp;selection=multiple&amp;sortColumnName=Name&amp;program=emxCommonIssue:getAllAssignee&amp;relationName=relationship_AssignedIssue&amp;header=emxComponents.Heading.Assignee&amp;HelpMarker=emxhelpissueassignees</href>
    <alt>emxComponents.Command.AssigneeList</alt>
    <code></code>
    <settings>
        <setting>
            <settingName>Registered Suite</settingName>
            <settingValue>Components</settingValue>
        </setting>
        <setting>
            <settingName>Target Location</settingName>
            <settingValue>content</settingValue>
        </setting>
    </settings>
    <userAccess/>
    <properties/>
</command>
