<?xml version="1.0" encoding="UTF-8" standalone="yes"?>
<command overlay="true">
    <name>PMCProjectBudgetFreeze</name>
    <symbolicName>command_PMCProjectBudgetFreeze</symbolicName>
    <dataObjectType>command</dataObjectType>
    <description></description>
    <label>emxProgramCentral.Budget.Freeze</label>
    <hidden>false</hidden>
    <href>${SUITE_DIR}/emxProgramCentralBudgetUtil.jsp?mode=freezeBudget</href>
    <alt></alt>
    <code></code>
    <settings>
        <setting>
            <settingName>Access Function</settingName>
            <settingValue>isCurrentStateFrozen</settingValue>
        </setting>
        <setting>
            <settingName>Access Program</settingName>
            <settingValue>emxProjectBudget</settingValue>
        </setting>
        <setting>
            <settingName>CmdName</settingName>
            <settingValue>PMCProjectBudgetFreeze</settingValue>
        </setting>
        <setting>
            <settingName>Image</settingName>
            <settingValue>${COMMON_DIR}/images/I_FreezeBudget32.png</settingValue>
        </setting>
        <setting>
            <settingName>Licensed Product</settingName>
            <settingValue>ENO_PRF_TP</settingValue>
        </setting>
        <setting>
            <settingName>Registered Suite</settingName>
            <settingValue>ProgramCentral</settingValue>
        </setting>
        <setting>
            <settingName>Submit</settingName>
            <settingValue>true</settingValue>
        </setting>
        <setting>
            <settingName>Target Location</settingName>
            <settingValue>listHidden</settingValue>
        </setting>
    </settings>
    <userAccess>
        <User>External Project User</User>
        <User>Project User</User>
        <User>VPLMViewer</User>
    </userAccess>
    <properties/>
</command>
