<?xml version="1.0" encoding="UTF-8" standalone="yes"?>
<command overlay="true">
    <name>PMCQuality</name>
    <symbolicName>command_PMCQuality</symbolicName>
    <dataObjectType>command</dataObjectType>
    <description>Quality Command Object</description>
    <label>emxFramework.Command.Quality</label>
    <hidden>false</hidden>
    <href>${COMMON_DIR}/emxIndentedTable.jsp?program=emxQuality:getAllProjectQuality,emxQuality:getControlledProjectQuality,emxQuality:getActiveProjectQuality&amp;programLabel=emxProgramCentral.Common.All,emxProgramCentral.Common.Controlled,emxProgramCentral.Common.ActiveProjects&amp;table=PMCProjectQuality&amp;toolbar=PMCProjectQualityToolbar&amp;selection=multiple&amp;Export=true&amp;sortColumnName=Name&amp;sortDirection=ascending&amp;header=emxProgramCentral.Common.QualityPageHeading&amp;HelpMarker=emxhelpqualitysummary</href>
    <alt>emxFramework.Command.Quality</alt>
    <code></code>
    <settings>
        <setting>
            <settingName>Image</settingName>
            <settingValue>COMMON_DIR/iconSmallQuality.gif</settingValue>
        </setting>
        <setting>
            <settingName>Licensed Product</settingName>
            <settingValue>ENO_PGE_TP</settingValue>
        </setting>
        <setting>
            <settingName>Registered Suite</settingName>
            <settingValue>ProgramCentral</settingValue>
        </setting>
        <setting>
            <settingName>Target Location</settingName>
            <settingValue>content</settingValue>
        </setting>
    </settings>
    <userAccess>
        <User>External Project User</User>
        <User>Project User</User>
        <User>VPLMViewer</User>
    </userAccess>
    <properties/>
</command>
