<?xml version="1.0" encoding="UTF-8" standalone="yes"?>
<command overlay="true">
    <name>QICAssociatedCAPARequestsSummary</name>
    <symbolicName>command_QICAssociatedCAPARequestsSummary</symbolicName>
    <dataObjectType>command</dataObjectType>
    <description>command to show the summary of associated CAPA Requests to an CAPA</description>
    <label>QIC.Common.CAPARequests</label>
    <hidden>false</hidden>
    <href>${COMMON_DIR}/emxIndentedTable.jsp?program=com.dassault_systemes.enovia.lsa.qic.services.ui.CAPA:getTableQICAssociatedCAPARequestsSummary&amp;table=QICAssociatedCAPARequestsSummary&amp;toolbar=QICAssociatedCAPARequestSummaryToolbar&amp;selection=multiple&amp;HelpMarker=emxhelpCAPArequests</href>
    <alt>QIC.Common.CAPARequests</alt>
    <code></code>
    <settings>
        <setting>
            <settingName>Licensed Product</settingName>
            <settingValue>ENO_QIC_TP,ENO_PGE_TP</settingValue>
        </setting>
        <setting>
            <settingName>Registered Suite</settingName>
            <settingValue>LQICAPA</settingValue>
        </setting>
    </settings>
    <userAccess/>
    <properties/>
</command>
