<?xml version="1.0" encoding="UTF-8" standalone="yes"?>
<command overlay="true">
    <name>RMTRemoveRequirementActionLink</name>
    <symbolicName>command_RMTRemoveRequirementActionLink</symbolicName>
    <dataObjectType>command</dataObjectType>
    <description>Command Object for Removing Selected Requirement(s).</description>
    <label>emxRequirements.ActionLink.Remove</label>
    <hidden>false</hidden>
    <href>${SUITE_DIR}/RequirementUtil.jsp?mode=disconnect</href>
    <alt></alt>
    <code></code>
    <settings>
        <setting>
            <settingName>Access Expression</settingName>
            <settingValue>(current != "Release" &amp;&amp; current != "Obsolete")</settingValue>
        </setting>
        <setting>
            <settingName>Confirm Message</settingName>
            <settingValue>emxRequirements.Alert.Remove</settingValue>
        </setting>
        <setting>
            <settingName>Image</settingName>
            <settingValue>${COMMON_DIR}/images/iconActionRemove.gif</settingValue>
        </setting>
        <setting>
            <settingName>Licensed Product</settingName>
            <settingValue>ENO_RMF_TP</settingValue>
        </setting>
        <setting>
            <settingName>Registered Suite</settingName>
            <settingValue>Requirements</settingValue>
        </setting>
        <setting>
            <settingName>Row Select</settingName>
            <settingValue>Multiple</settingValue>
        </setting>
        <setting>
            <settingName>Submit</settingName>
            <settingValue>true</settingValue>
        </setting>
        <setting>
            <settingName>Target Location</settingName>
            <settingValue>listHidden</settingValue>
        </setting>
    </settings>
    <userAccess>
        <User>Product Manager</User>
        <User>Requirement Manager</User>
        <User>Software Engineer</User>
        <User>Software Engineering Manager</User>
        <User>Software Project Manager</User>
        <User>System Conversion Manager</User>
        <User>System Transition Manager</User>
        <User>VPLMCreator</User>
        <User>VPLMProjectAdministrator</User>
    </userAccess>
    <properties/>
</command>
