<?xml version="1.0" encoding="UTF-8" standalone="yes"?>
<menu overlay="true">
    <name>IEFCommonFindCancelBottomActionBar</name>
    <symbolicName>menu_IEFCommonFindCancelBottomActionBar</symbolicName>
    <dataObjectType>menu</dataObjectType>
    <description>Common Find Cancel Bottom ActionBar</description>
    <label></label>
    <hidden>false</hidden>
    <href></href>
    <alt></alt>
    <menuItems/>
    <commandItems>
        <commandItem>IEFCommonFindButtonActionLink</commandItem>
        <commandItem>IEFCommonCancelButtonActionLink</commandItem>
    </commandItems>
    <settings>
        <setting>
            <settingName>Access Function</settingName>
            <settingValue>doNotShowForAppletFree</settingValue>
        </setting>
        <setting>
            <settingName>Access Program</settingName>
            <settingValue>IEFActionAccess</settingValue>
        </setting>
        <setting>
            <settingName>Registered Suite</settingName>
            <settingValue>DesignerCentral</settingValue>
        </setting>
    </settings>
    <properties/>
</menu>
