<?xml version="1.0" encoding="UTF-8" standalone="yes"?>
<menu overlay="true">
    <name>PQCINQMyInquiryActionMenu</name>
    <symbolicName>menu_PQCINQMyInquiryActionMenu</symbolicName>
    <dataObjectType>menu</dataObjectType>
    <description></description>
    <label>PQC.Common.Actions</label>
    <hidden>false</hidden>
    <href></href>
    <alt></alt>
    <menuItems/>
    <commandItems>
        <commandItem>TicketMgmtWorkQueueAccept</commandItem>
        <commandItem>TicketMgmtWorkQueueSubmitToReview</commandItem>
        <commandItem>TicketMgmtWorkQueueTransferOwnership</commandItem>
        <commandItem>TicketMgmtWorkQueueInvalidate</commandItem>
        <commandItem>TicketMgmtWorkQueueClose</commandItem>
        <commandItem>TicketMgmtWorkQueueDelete</commandItem>
        <commandItem>TicketMgmtAddAssigneesToTicket</commandItem>
    </commandItems>
    <settings>
        <setting>
            <settingName>Image</settingName>
            <settingValue>${COMMON_DIR}/images/iconActionActions.png</settingValue>
        </setting>
        <setting>
            <settingName>Registered Suite</settingName>
            <settingValue>ESRInquiry</settingValue>
        </setting>
    </settings>
    <properties/>
</menu>
