<?xml version="1.0" encoding="UTF-8" standalone="yes"?>
<interface overlay="true">
    <name>ToolingComponent</name>
    <symbolicName>interface_ToolingComponent</symbolicName>
    <dataObjectType>interface</dataObjectType>
    <description></description>
    <parent>ToolingExtension</parent>
    <hidden>false</hidden>
    <abstract>true</abstract>
    <attrbutes>
        <attribute>ToolingComponent.V_TlgDiameter</attribute>
        <attribute>ToolingComponent.V_TlgHeight</attribute>
        <attribute>ToolingComponent.V_TlgLength</attribute>
        <attribute>ToolingComponent.V_TlgThickness</attribute>
        <attribute>ToolingComponent.V_TlgWidth</attribute>
        <attribute>ToolingComponent.V_TlgBOMVisibility</attribute>
    </attrbutes>
    <allowedTypes>
        <type>VPMReference</type>
    </allowedTypes>
    <allowedRelationships/>
    <properties/>
</interface>
