{
    "by": "By",
    "in": "in",
    "ReportAbuse": "Report abuse",
    "Edit": "Edit",
    "Delete": "Delete",
    "Confirm": "Confirm",
    "Highlight" : "Highlight",
    "ContentDeletionMsg": "Are you sure you want to delete this content?",
    "ContentDeleted" : "The content was successfully deleted.",
    "ContentNotDeleted" : "Sorry, the content could not be deleted. Please try again later.",
    "Loading": "Loading...",
    "ConvertToIdea" : "Transfer to idea",
    "Menu": "Menu",
    "ContentList": "Content List",
    "HighlightSuccess" : "Your content has been successfully highlighted.",
    "HighlightFailure" : "Sorry, the content could not be highlighted. Pelase try again later.",
    "UnhighlightSuccess" : "Highlight has been successfully removed.",
    "UnhighlightFailure" : "Sorry, the content could not be unhighlighted. Please try again later.",
    "HideHighlightSuccess": "Highlight is now hidden",
    "HideHighlightFailure": "Sorry, the highlight could not be hidden. Please try again later.",
    "HideHighlightConfirmationTitle" : "Are you sure you want to hide this highlighted content?",
    "HideHighlightConfirmationModalMsg" : "Once the highlighted content is hidden you won't be able to see it as highlighted but you can still find it in the feed.",
    "HideHighlight": "Hide Highlight",
    "Unhighlight" : "Remove Highlight",
    "Edited" : "Edited",
    "Moderated" : "Moderated",
    "EditedTooltip" : "Edited {prettyDate}",
    "ModeratedTooltip" : "Moderated {prettyDate}",
    "RevertToThisRevision" : "Revert to this revision"
}
