<?xml version="1.0" encoding="UTF-8" standalone="yes"?>
<attribute overlay="true">
    <name>Audit Device</name>
    <symbolicName>attribute_AuditDevice</symbolicName>
    <dataObjectType>attribute</dataObjectType>
    <description>LQIAudit</description>
    <type>string</type>
    <defaultValue></defaultValue>
    <dimension></dimension>
    <maxLength>0</maxLength>
    <scope></scope>
    <owner></owner>
    <valueType>singleval</valueType>
    <isHidden>false</isHidden>
    <resetOnClone>false</resetOnClone>
    <resetOnRevision>false</resetOnRevision>
    <multiline>true</multiline>
    <ranges>
        <drRange>
            <range>!=</range>
            <valueOne>dummy</valueOne>
            <inclusiveValueOne>false</inclusiveValueOne>
            <valueTwo></valueTwo>
            <inclusiveValueTwo>false</inclusiveValueTwo>
        </drRange>
        <drRange>
            <range>=</range>
            <valueOne>Device1</valueOne>
            <inclusiveValueOne>false</inclusiveValueOne>
            <valueTwo></valueTwo>
            <inclusiveValueTwo>false</inclusiveValueTwo>
        </drRange>
        <drRange>
            <range>=</range>
            <valueOne>Device2</valueOne>
            <inclusiveValueOne>false</inclusiveValueOne>
            <valueTwo></valueTwo>
            <inclusiveValueTwo>false</inclusiveValueTwo>
        </drRange>
    </ranges>
    <triggers/>
    <properties/>
</attribute>
