<?xml version="1.0" encoding="UTF-8" standalone="yes"?>
<attribute overlay="true">
    <name>controllingchangeid</name>
    <symbolicName>attribute_controllingchangeid</symbolicName>
    <dataObjectType>attribute</dataObjectType>
    <description>Controlling change Ids of the the entity.</description>
    <type>string</type>
    <defaultValue></defaultValue>
    <dimension></dimension>
    <maxLength>0</maxLength>
    <scope></scope>
    <owner></owner>
    <valueType>multival</valueType>
    <isHidden>false</isHidden>
    <resetOnClone>true</resetOnClone>
    <resetOnRevision>true</resetOnRevision>
    <multiline>false</multiline>
    <ranges/>
    <triggers/>
    <properties/>
</attribute>
