<?xml version="1.0" encoding="UTF-8" standalone="yes"?>
<type overlay="true">
    <name>DRLTools Export Target Custom</name>
    <symbolicName>type_DRLToolsExportTargetCustom</symbolicName>
    <dataObjectType>type</dataObjectType>
    <description>DRLTools Export Target Custom</description>
    <parentName>DRLTools Export Target</parentName>
    <hidden>false</hidden>
    <abstract>false</abstract>
    <attributes>
        <attribute>drlArg1</attribute>
        <attribute>drlArg1Description</attribute>
        <attribute>drlArg2</attribute>
        <attribute>drlArg2Description</attribute>
        <attribute>drlArg3</attribute>
        <attribute>drlArg3Description</attribute>
        <attribute>drlArg4</attribute>
        <attribute>drlArg4Description</attribute>
        <attribute>drlArg5</attribute>
        <attribute>drlArg5Description</attribute>
        <attribute>drlArg6</attribute>
        <attribute>drlArg6Description</attribute>
        <attribute>drlJavaClassName</attribute>
        <attribute>drlMultilineArg1</attribute>
        <attribute>drlMultilineArg1Description</attribute>
        <attribute>drlMultilineArg2</attribute>
        <attribute>drlMultilineArg2Description</attribute>
        <attribute>drlMultilineArg3</attribute>
        <attribute>drlMultilineArg3Description</attribute>
    </attributes>
    <triggers/>
    <properties/>
</type>
