<?xml version="1.0" encoding="UTF-8" standalone="yes"?>
<type overlay="true">
    <name>SolidWorksInteg-GlobalConfig</name>
    <symbolicName>type_SolidWorksInteg-GlobalConfig</symbolicName>
    <dataObjectType>type</dataObjectType>
    <description>Global Config Object for SW</description>
    <parentName>MCADInteg-GlobalConfig</parentName>
    <hidden>false</hidden>
    <abstract>false</abstract>
    <attributes>
        <attribute>IEF-AutoNameSeries</attribute>
        <attribute>IEF-CADToMxMandatoryAttrMapping</attribute>
        <attribute>IEF-CSEDerivedOutputOptions</attribute>
        <attribute>IEF-CSEDisabledCommandsList</attribute>
        <attribute>IEF-EnforceLockLocation</attribute>
        <attribute>IEF-ModificationEvents</attribute>
        <attribute>IEF-ObjectAndFileNameDifferent</attribute>
        <attribute>IEF-SetDefaultFamilyObjectRevisionMode</attribute>
        <attribute>IEF-UnsupportedCharacterMapping</attribute>
        <attribute>IEF-UserExitEventRegistration</attribute>
        <attribute>MCADInteg-DisableConfigurations</attribute>
        <attribute>MCADInteg-FamilyInstanceMapping</attribute>
        <attribute>MCADInteg-FileReadOnlyBehavior</attribute>
        <attribute>MCADInteg-KeepLocalReferencesOnCheckout</attribute>
        <attribute>MCADInteg-LockReadOnlyFile</attribute>
        <attribute>MCADInteg-NamingStrategy</attribute>
        <attribute>MCADInteg-TraverseDrwOnBothSides</attribute>
        <attribute>MCADInteg-VirtualComponentSupport</attribute>
        <attribute>SLW-AddInRegistration</attribute>
        <attribute>SLW-CheckInBlockRemoteReferences</attribute>
        <attribute>SLW-CheckInPermitIncomplete</attribute>
        <attribute>SLW-CheckoutPermitPartialGet</attribute>
        <attribute>SLW-ConfigurationFilter</attribute>
        <attribute>SLW-PDS-UserSettings</attribute>
    </attributes>
    <triggers/>
    <properties/>
</type>
