{
	"title" : "Title",
    "placeholderTitle" : "Enter title...",
    "errorEmptyTitle" : "The title cannot be empty",
    "errorCharacterTitle" : "The title cannot include the characters \\ \" # $ @ % * , ? < > [ ] | / : . '",
    "errorSpaceTitle" : "The title cannot finish by a space",
    "description" : "Description",
    "placeholderDescription" : "Enter title...",
    "errorCharacterDescription" : "The description cannot include the characters",
    "visibility" : "Visibility",
    "private" : "Private",
    "privateDetail" : "Content visible by members only",
    "protected" : "Protected",
    "protectedDetail" : "Content with maturity 'Released' or 'Obsolete' visible by all users",
    "public" : "Public",
    "publicDetail" : "Content visible by all users",
    "family" : "Family",
    "design" : "Design",
    "designDetail" : "Collaborative storage to manage any kind of content",
    "standard" : "Standard",
	"standardDetail" : "Collaborative storage to manage standard content",
    "create" : "Create",
    "cancel" : "Cancel"
}
