<?xml version="1.0" encoding="UTF-8" standalone="yes"?>
<webForm overlay="true">
    <name>NewDeploymentExtensionForm</name>
    <symbolicName>form_NewDeploymentExtensionForm</symbolicName>
    <dataObjectType>webForm</dataObjectType>
    <description>New Deployment Extension Form</description>
    <type></type>
    <hidden>false</hidden>
    <fields>
        <field>
            <name>deployExtName</name>
            <description></description>
            <expression>
                <expression></expression>
                <appliesTo></appliesTo>
                <hasCustomLabel>true</hasCustomLabel>
                <customLabel>emxDataSpecialization.label.Name</customLabel>
            </expression>
            <href></href>
            <alt></alt>
            <rangeHref></rangeHref>
            <updateUrl></updateUrl>
            <userAccess/>
            <settings>
                <setting>
                    <settingName>Registered Suite</settingName>
                    <settingValue>DataSpecialization</settingValue>
                </setting>
                <setting>
                    <settingName>Required</settingName>
                    <settingValue>true</settingValue>
                </setting>
                <setting>
                    <settingName>Validate</settingName>
                    <settingValue>checkNames</settingValue>
                </setting>
            </settings>
        </field>
        <field>
            <name>deployTypes</name>
            <description></description>
            <expression>
                <expression></expression>
                <appliesTo></appliesTo>
                <hasCustomLabel>true</hasCustomLabel>
                <customLabel>emxDataSpecialization.label.DeployExtensionTypes</customLabel>
            </expression>
            <href></href>
            <alt></alt>
            <rangeHref>${COMMON_DIR}/emxIndentedTable.jsp?table=DeploymentPackagesListTable&amp;toolbar=none&amp;program=emxPackagesConfigurationProgram:getDeploymentExtensionsPackagesList&amp;expandProgram=emxPackagesConfigurationProgram:getDeploymentExtensionsTypesList&amp;freezePane=packageName&amp;selection=multiple&amp;header=emxDataSpecialization.label.DeployExtensionTypesList&amp;submitURL=../DataSpecialization/emxPackagesConfigurationSubmitDeploymentObjects.jsp&amp;showPageURLIcon=false&amp;customize=false&amp;showClipboard=false&amp;objectCompare=false&amp;jpoAppServerParamList=session:DataCustoCacheIndex&amp;submitLabel=emxDataSpecialization.Submit</rangeHref>
            <updateUrl></updateUrl>
            <userAccess/>
            <settings>
                <setting>
                    <settingName>Registered Suite</settingName>
                    <settingValue>DataSpecialization</settingValue>
                </setting>
                <setting>
                    <settingName>Required</settingName>
                    <settingValue>true</settingValue>
                </setting>
                <setting>
                    <settingName>Show Clear Button</settingName>
                    <settingValue>true</settingValue>
                </setting>
                <setting>
                    <settingName>Submit</settingName>
                    <settingValue>true</settingValue>
                </setting>
            </settings>
        </field>
        <field>
            <name>staticAssociation</name>
            <description></description>
            <expression>
                <expression></expression>
                <appliesTo></appliesTo>
                <hasCustomLabel>true</hasCustomLabel>
                <customLabel>emxDataSpecialization.label.StaticAssociation</customLabel>
            </expression>
            <href></href>
            <alt></alt>
            <rangeHref></rangeHref>
            <updateUrl></updateUrl>
            <userAccess/>
            <settings>
                <setting>
                    <settingName>Editable</settingName>
                    <settingValue>true</settingValue>
                </setting>
                <setting>
                    <settingName>Field Type</settingName>
                    <settingValue>program</settingValue>
                </setting>
                <setting>
                    <settingName>Input Type</settingName>
                    <settingValue>combobox</settingValue>
                </setting>
                <setting>
                    <settingName>Range Function</settingName>
                    <settingValue>getFalseTrue</settingValue>
                </setting>
                <setting>
                    <settingName>Range Program</settingName>
                    <settingValue>emxPackagesConfigurationProgram</settingValue>
                </setting>
                <setting>
                    <settingName>Registered Suite</settingName>
                    <settingValue>DataSpecialization</settingValue>
                </setting>
                <setting>
                    <settingName>Remove Range Blank</settingName>
                    <settingValue>true</settingValue>
                </setting>
                <setting>
                    <settingName>Sort Range Values</settingName>
                    <settingValue>disable</settingValue>
                </setting>
            </settings>
        </field>
        <field>
            <name>userComment</name>
            <description></description>
            <expression>
                <expression></expression>
                <appliesTo></appliesTo>
                <hasCustomLabel>true</hasCustomLabel>
                <customLabel>emxDataSpecialization.label.Comment</customLabel>
            </expression>
            <href></href>
            <alt></alt>
            <rangeHref></rangeHref>
            <updateUrl></updateUrl>
            <userAccess/>
            <settings>
                <setting>
                    <settingName>Input Type</settingName>
                    <settingValue>textarea</settingValue>
                </setting>
                <setting>
                    <settingName>Registered Suite</settingName>
                    <settingValue>DataSpecialization</settingValue>
                </setting>
                <setting>
                    <settingName>Required</settingName>
                    <settingValue>false</settingValue>
                </setting>
            </settings>
        </field>
    </fields>
    <properties/>
</webForm>
